Metadata-Version: 1.0
Name: dsb-gauss-bin
Version: 0.1
Summary: Gaussian distributions
Home-page: UNKNOWN
Author: Thariq Ramadhan
Author-email: UNKNOWN
License: UNKNOWN
Platform: UNKNOWN
